MANIFEST.in
README.rst
setup.cfg
setup.py
tests/__init__.py
tests/base.py
tests/mingmodel.py
tests/sqlamodel.py
tests/test_controller.py
tests/controllers/__init__.py
tests/controllers/root.py
tests/templates/__init__.py
tgapp_permissions.egg-info/PKG-INFO
tgapp_permissions.egg-info/SOURCES.txt
tgapp_permissions.egg-info/dependency_links.txt
tgapp_permissions.egg-info/entry_points.txt
tgapp_permissions.egg-info/not-zip-safe
tgapp_permissions.egg-info/requires.txt
tgapp_permissions.egg-info/top_level.txt
tgapppermissions/__init__.py
tgapppermissions/bootstrap.py
tgapppermissions/helpers.py
tgapppermissions/controllers/__init__.py
tgapppermissions/controllers/root.py
tgapppermissions/lib/__init__.py
tgapppermissions/lib/forms.py
tgapppermissions/lib/helpers.py
tgapppermissions/model/__init__.py
tgapppermissions/public/__init__.py
tgapppermissions/public/css/style.css
tgapppermissions/public/images/star.png
tgapppermissions/templates/__init__.py
tgapppermissions/templates/edit_permission.xhtml
tgapppermissions/templates/index.xhtml
tgapppermissions/templates/new_permission.xhtml
tgapppermissions/templates/users.xhtml