Metadata-Version: 2.1
Name: tgapp-permissions
Version: 0.3.2
Summary: Permission management for web application in turbogears2
Home-page: https://github.com/axant/tgapp-permissions
Author: Axant, Vincenzo Castiglia
Author-email: vincenzo.castiglia@axant.it
License: UNKNOWN
Keywords: turbogears2.application
Platform: UNKNOWN
Provides-Extra: testing
